{"ok":true,"data":{"buckets":[{"id":"5224438e-3d8d-41bf-8dab-6a8987a3217d","titleRaw":"","descriptionRaw":"","titleEnhanced":"","descriptionEnhanced":"","quantity":null,"price":null,"imageUrls":[],"status":"EMPTY","shopifyCreated":false,"shopifyProductId":"","shopifyProductUrl":"","instagramPublished":false,"instagramPostId":"","instagramPostUrl":"","errorMessage":"","trashedAt":"","deleteAfterAt":"","createdAt":"2026-04-20T20:12:23.871+00:00","updatedAt":"2026-04-20T20:12:23.966+00:00"},{"id":"631c57d3-050d-41c1-9143-23ee39bdfb70","titleRaw":"","descriptionRaw":"","titleEnhanced":"","descriptionEnhanced":"","quantity":null,"price":null,"imageUrls":[],"status":"EMPTY","shopifyCreated":false,"shopifyProductId":"","shopifyProductUrl":"","instagramPublished":false,"instagramPostId":"","instagramPostUrl":"","errorMessage":"","trashedAt":"","deleteAfterAt":"","createdAt":"2026-04-20T20:12:24.36+00:00","updatedAt":"2026-04-20T20:12:24.426+00:00"},{"id":"ae1ffa81-c39d-47ab-8b30-ba4c23dad955","titleRaw":"","descriptionRaw":"","titleEnhanced":"","descriptionEnhanced":"","quantity":null,"price":null,"imageUrls":[],"status":"EMPTY","shopifyCreated":false,"shopifyProductId":"","shopifyProductUrl":"","instagramPublished":false,"instagramPostId":"","instagramPostUrl":"","errorMessage":"","trashedAt":"","deleteAfterAt":"","createdAt":"2026-04-20T20:12:24.726+00:00","updatedAt":"2026-04-20T20:12:24.816+00:00"},{"id":"aa94cf9d-d423-4b9b-859a-9b6b8ff09ceb","titleRaw":"","descriptionRaw":"","titleEnhanced":"","descriptionEnhanced":"","quantity":null,"price":null,"imageUrls":[],"status":"EMPTY","shopifyCreated":false,"shopifyProductId":"","shopifyProductUrl":"","instagramPublished":false,"instagramPostId":"","instagramPostUrl":"","errorMessage":"","trashedAt":"","deleteAfterAt":"","createdAt":"2026-04-20T20:12:25.148+00:00","updatedAt":"2026-04-20T20:12:25.232+00:00"},{"id":"48b7f77e-861c-47d8-8728-af3242bce7fd","titleRaw":"","descriptionRaw":"","titleEnhanced":"","descriptionEnhanced":"","quantity":null,"price":null,"imageUrls":[],"status":"EMPTY","shopifyCreated":false,"shopifyProductId":"","shopifyProductUrl":"","instagramPublished":false,"instagramPostId":"","instagramPostUrl":"","errorMessage":"","trashedAt":"","deleteAfterAt":"","createdAt":"2026-04-20T20:12:25.612+00:00","updatedAt":"2026-04-20T20:12:25.693+00:00"},{"id":"bf84a907-037b-4abd-88bc-ee2c7423c8f0","titleRaw":"","descriptionRaw":"","titleEnhanced":"","descriptionEnhanced":"","quantity":null,"price":null,"imageUrls":[],"status":"EMPTY","shopifyCreated":false,"shopifyProductId":"","shopifyProductUrl":"","instagramPublished":false,"instagramPostId":"","instagramPostUrl":"","errorMessage":"","trashedAt":"","deleteAfterAt":"","createdAt":"2026-04-20T20:12:25.959+00:00","updatedAt":"2026-04-20T20:12:26.017+00:00"},{"id":"dbd31c50-b779-4c8a-922a-7562dbb559c7","titleRaw":"","descriptionRaw":"","titleEnhanced":"","descriptionEnhanced":"","quantity":null,"price":null,"imageUrls":[],"status":"EMPTY","shopifyCreated":false,"shopifyProductId":"","shopifyProductUrl":"","instagramPublished":false,"instagramPostId":"","instagramPostUrl":"","errorMessage":"","trashedAt":"","deleteAfterAt":"","createdAt":"2026-04-20T20:12:27.282+00:00","updatedAt":"2026-04-20T20:12:27.377+00:00"},{"id":"b30a770c-6f0b-4522-bb03-ca23bd7303ea","titleRaw":"","descriptionRaw":"","titleEnhanced":"","descriptionEnhanced":"","quantity":null,"price":null,"imageUrls":[],"status":"EMPTY","shopifyCreated":false,"shopifyProductId":"","shopifyProductUrl":"","instagramPublished":false,"instagramPostId":"","instagramPostUrl":"","errorMessage":"","trashedAt":"","deleteAfterAt":"","createdAt":"2026-04-20T20:12:27.623+00:00","updatedAt":"2026-04-20T20:12:27.68+00:00"},{"id":"09f3fc65-05d7-4ffb-9bb7-cfcbdc838df3","titleRaw":"","descriptionRaw":"","titleEnhanced":"","descriptionEnhanced":"","quantity":null,"price":null,"imageUrls":[],"status":"EMPTY","shopifyCreated":false,"shopifyProductId":"","shopifyProductUrl":"","instagramPublished":false,"instagramPostId":"","instagramPostUrl":"","errorMessage":"","trashedAt":"","deleteAfterAt":"","createdAt":"2026-04-20T20:12:27.931+00:00","updatedAt":"2026-04-20T20:12:27.983+00:00"},{"id":"a100515b-26e6-4221-a5f1-c2ac566a737d","titleRaw":"","descriptionRaw":"","titleEnhanced":"","descriptionEnhanced":"","quantity":null,"price":null,"imageUrls":[],"status":"EMPTY","shopifyCreated":false,"shopifyProductId":"","shopifyProductUrl":"","instagramPublished":false,"instagramPostId":"","instagramPostUrl":"","errorMessage":"","trashedAt":"","deleteAfterAt":"","createdAt":"2026-04-20T20:12:28.219+00:00","updatedAt":"2026-04-20T20:12:28.269+00:00"},{"id":"622d5f71-f169-4db8-ada5-f51eda4e8de2","titleRaw":"","descriptionRaw":"","titleEnhanced":"","descriptionEnhanced":"","quantity":null,"price":null,"imageUrls":[],"status":"EMPTY","shopifyCreated":false,"shopifyProductId":"","shopifyProductUrl":"","instagramPublished":false,"instagramPostId":"","instagramPostUrl":"","errorMessage":"","trashedAt":"","deleteAfterAt":"","createdAt":"2026-04-20T20:12:28.504+00:00","updatedAt":"2026-04-20T20:12:28.543+00:00"},{"id":"ea72a79d-d9cd-4b8c-ad39-00435176a056","titleRaw":"","descriptionRaw":"","titleEnhanced":"","descriptionEnhanced":"","quantity":null,"price":null,"imageUrls":[],"status":"EMPTY","shopifyCreated":false,"shopifyProductId":"","shopifyProductUrl":"","instagramPublished":false,"instagramPostId":"","instagramPostUrl":"","errorMessage":"","trashedAt":"","deleteAfterAt":"","createdAt":"2026-04-20T20:12:28.8+00:00","updatedAt":"2026-04-20T20:12:28.847+00:00"},{"id":"8ee3d614-b2d0-4ec2-a519-3a9f50b5eeb6","titleRaw":"","descriptionRaw":"","titleEnhanced":"","descriptionEnhanced":"","quantity":null,"price":null,"imageUrls":[],"status":"EMPTY","shopifyCreated":false,"shopifyProductId":"","shopifyProductUrl":"","instagramPublished":false,"instagramPostId":"","instagramPostUrl":"","errorMessage":"","trashedAt":"","deleteAfterAt":"","createdAt":"2026-04-20T20:12:31.036+00:00","updatedAt":"2026-04-20T20:12:31.081+00:00"},{"id":"17e270b6-8e08-4fd4-a41e-aab40c73fe0b","titleRaw":"","descriptionRaw":"","titleEnhanced":"","descriptionEnhanced":"","quantity":null,"price":null,"imageUrls":[],"status":"EMPTY","shopifyCreated":false,"shopifyProductId":"","shopifyProductUrl":"","instagramPublished":false,"instagramPostId":"","instagramPostUrl":"","errorMessage":"","trashedAt":"","deleteAfterAt":"","createdAt":"2026-04-20T20:13:09.464+00:00","updatedAt":"2026-04-20T20:13:09.523+00:00"}],"trashedBuckets":[]}}